{"ap-500":{"title":"AP-500 &quot;Hey, don&#039;t run away ...&quot; Tutor teacher and girl","image":"https://fourhoi.com/ap-500/cover-n.jpg","driveId":null},"ap-498":{"title":"AP-498 Continuous Bukkake Bookstore Creampie Slut ● - M","image":"https://fourhoi.com/ap-498/cover-n.jpg","driveId":null},"atom-309":{"title":"ATOM-309 Panchira barrage! Only for amateurs! Power gen","image":"https://fourhoi.com/atom-309/cover-n.jpg","driveId":null},"ap-501":{"title":"AP-501 Shoplifting Young Wife Backyard Restraint Wheel ","image":"https://fourhoi.com/ap-501/cover-n.jpg","driveId":null},"atom-308":{"title":"ATOM-308 Only for amateurs! If you feel crisp and fall,","image":"https://fourhoi.com/atom-308/cover-n.jpg","driveId":null},"ap-499":{"title":"AP-499 Love Hotel Restraint Fixed Aphrodisiac Vibe Aban","image":"https://fourhoi.com/ap-499/cover-n.jpg","driveId":null},"atom-310":{"title":"ATOM-310 Panchira barrage! Butt fir fir! Only for amate","image":"https://fourhoi.com/atom-310/cover-n.jpg","driveId":null},"atom-307":{"title":"ATOM-307 Skirt! Breast chiller is natural! Manchira! Po","image":"https://fourhoi.com/atom-307/cover-n.jpg","driveId":null},"av-180":{"title":"AV-180 Wife&#039;s behavior witnessing her husband&#039;s masturb","image":"https://fourhoi.com/av-180/cover-n.jpg","driveId":null},"av-179":{"title":"AV-179 My mother&#039;s friend is a club mom Saori Miyamoto ","image":"https://fourhoi.com/av-179/cover-n.jpg","driveId":null},"adn-148":{"title":"ADN-148 Unfaithful hierarchy Saeko Matsushita - MissAV ","image":"https://fourhoi.com/adn-148/cover-n.jpg","driveId":null},"adn-146":{"title":"ADN-146 ATTACKERS x S1 special collaboration project Yo","image":"https://fourhoi.com/adn-146/cover-n.jpg","driveId":null},"adn-147":{"title":"ADN-147 Hold it, that&#039;s all you need to do ... Kizaki J","image":"https://fourhoi.com/adn-147/cover-n.jpg","driveId":null},"atid-291":{"title":"ATID-291 This is you, isn&#039;t it Suzu Harumiya - MissAV |","image":"https://fourhoi.com/atid-291/cover-n.jpg","driveId":null},"adn-149":{"title":"ADN-149 Fucked in front of my husband ● Midnight affair","image":"https://fourhoi.com/adn-149/cover-n.jpg","driveId":null},"abp-676":{"title":"ABP-676 Rui Hasegawa Namanakadashi 19 Conceives everyon","image":"https://fourhoi.com/abp-676/cover-n.jpg","driveId":null},"ama-007":{"title":"AMA-007 A masterpiece of SEX. Shocking test shots of di","image":"https://fourhoi.com/ama-007/cover-n.jpg","driveId":null},"apaa-377":{"title":"APAA-377 A female college student whose obscene breasts","image":"https://fourhoi.com/apaa-377/cover-n.jpg","driveId":null},"apns-034":{"title":"APNS-034 Two playhood friends Ai and Nami The smell of ","image":"https://fourhoi.com/apns-034/cover-n.jpg","driveId":null},"apkh-052":{"title":"APKH-052 When I brought the neat and intellectual beaut","image":"https://fourhoi.com/apkh-052/cover-n.jpg","driveId":null},"avsa-049":{"title":"AVSA-049 CFNM Clothes Secret Nao Wakana - MissAV | Watc","image":"https://fourhoi.com/avsa-049/cover-n.jpg","driveId":null},"apns-033":{"title":"APNS-033 Beautiful wife dropped into a trap &quot;Every day,","image":"https://fourhoi.com/apns-033/cover-n.jpg","driveId":null},"aqsh-013":{"title":"AQSH-013 My wife was taken down. I was captivated by th","image":"https://fourhoi.com/aqsh-013/cover-n.jpg","driveId":null},"aqsh-014":{"title":"AQSH-014 My wife was taken down. When I let my boss tak","image":"https://fourhoi.com/aqsh-014/cover-n.jpg","driveId":null},"apao-026":{"title":"APAO-026 Aurora Project Digest 48 Bursts December 2016-","image":"https://fourhoi.com/apao-026/cover-n.jpg","driveId":null},"aukg-409":{"title":"AUKG-409 Do Mature Woman Fifty Lesbians Sayuri Takarada","image":"https://fourhoi.com/aukg-409/cover-n.jpg","driveId":null},"aukb-081":{"title":"AUKB-081 Beautiful Mature Woman Lesbian Swastika BEST 4","image":"https://fourhoi.com/aukb-081/cover-n.jpg","driveId":null},"armg-280":{"title":"ARMG-280 Private thigh job school 2 - Miyazaki Aya - Mi","image":"https://fourhoi.com/armg-280/cover-n.jpg","driveId":null},"abp-674":{"title":"ABP-674 Ren Yoshikawa&#039;s finest brush wholesale 18 E cup","image":"https://fourhoi.com/abp-674/cover-n.jpg","driveId":null},"abp-673":{"title":"ABP-673 Derived from natural ingredients Kirari Sena 12","image":"https://fourhoi.com/abp-673/cover-n.jpg","driveId":null},"armg-279":{"title":"ARMG-279 It was talked about that the warmth of Mako ov","image":"https://fourhoi.com/armg-279/cover-n.jpg","driveId":null},"abp-675":{"title":"ABP-675 Hinata Mio Hinata Nakadashi 18 All the whole st","image":"https://fourhoi.com/abp-675/cover-n.jpg","driveId":null},"arm-645":{"title":"ARM-645 Is it okay to release semen to my thighs and pa","image":"https://fourhoi.com/arm-645/cover-n.jpg","driveId":null},"arm-644":{"title":"ARM-644 Pile driving piston cowgirl 3 - Wakaba Onoe - M","image":"https://fourhoi.com/arm-644/cover-n.jpg","driveId":null},"aka-050":{"title":"AKA-050 Amateur uniform beauty 10 Barrage hard play tha","image":"https://fourhoi.com/aka-050/cover-n.jpg","driveId":null},"ap-494":{"title":"AP-494 Piledriver Panty Bukkake Bookstore Slut ● - Miss","image":"https://fourhoi.com/ap-494/cover-n.jpg","driveId":null},"ap-492":{"title":"AP-492 Don&#039;t touch your daughter! Mother-daughter &quot;subs","image":"https://fourhoi.com/ap-492/cover-n.jpg","driveId":null},"ap-495":{"title":"AP-495 Unequaled Boy Big Breasts Sister-in-law Continuo","image":"https://fourhoi.com/ap-495/cover-n.jpg","driveId":null},"ap-496":{"title":"AP-496 Overtime OL Dark Restraint Blindfold Squid Slut ","image":"https://fourhoi.com/ap-496/cover-n.jpg","driveId":null},"agr-024":{"title":"AGR-024 Yuka Honjo, the wife of the sailor suit next do","image":"https://fourhoi.com/agr-024/cover-n.jpg","driveId":null},"anb-139":{"title":"ANB-139 I&#039;m Seduced By A Beautiful And Nasty Aunt&#039;s Bom","image":"https://fourhoi.com/anb-139/cover-n.jpg","driveId":null},"awd-099":{"title":"AWD-099 play Mother&#039;s Ass ~ Super Muchimuchi Beauty Mot","image":"https://fourhoi.com/awd-099/cover-n.jpg","driveId":null},"ast-051":{"title":"AST-051 I Became A Mother&#039;s Toy Slut Mother-in-law 12 P","image":"https://fourhoi.com/ast-051/cover-n.jpg","driveId":null},"ako-301":{"title":"AKO-301 MAKOTO - MissAV | Watch HD JAV Online | Free &amp; ","image":"https://fourhoi.com/ako-301/cover-n.jpg","driveId":null},"avvr-290":{"title":"AVVR-290 [VR] Flirting Masturbation Yukari Miyazawa - M","image":"https://fourhoi.com/avvr-290/cover-n.jpg","driveId":null},"ama-006":{"title":"AMA-006 A masterpiece of SEX. Shocking test shots of di","image":"https://fourhoi.com/ama-006/cover-n.jpg","driveId":null},"aka-049":{"title":"AKA-049 Superb BODY AV Debut Bust 95cm H Cup Perfect Bo","image":"https://fourhoi.com/aka-049/cover-n.jpg","driveId":null},"abp-670":{"title":"ABP-670 Restraint sexual intercourse that makes a beaut","image":"https://fourhoi.com/abp-670/cover-n.jpg","driveId":null},"abp-671":{"title":"ABP-671 Climax sex ACT.06 You can only pull out by impa","image":"https://fourhoi.com/abp-671/cover-n.jpg","driveId":null},"afs-028":{"title":"AFS-028 Married Woman Picking Up Girls Home Creampie x ","image":"https://fourhoi.com/afs-028/cover-n.jpg","driveId":null},"abp-672":{"title":"ABP-672 Life&#039;s First Trance State Super Iki Cum Sex 41 ","image":"https://fourhoi.com/abp-672/cover-n.jpg","driveId":null},"asw-223":{"title":"ASW-223 MANIAC SEMEN Special Edition Cum Share House! W","image":"https://fourhoi.com/asw-223/cover-n.jpg","driveId":null},"ambi-085":{"title":"AMBI-085 Criminal ● Demolished daughter Mimi Yazawa 18 ","image":"https://fourhoi.com/ambi-085/cover-n.jpg","driveId":null},"avvr-289":{"title":"AVVR-289 [VR] Good Morning Creampie SEX Yu Shinoda - Sh","image":"https://fourhoi.com/avvr-289/cover-n.jpg","driveId":null},"abp-669":{"title":"ABP-669 Spocos sweaty SEX 4 production! Athlete-based S","image":"https://fourhoi.com/abp-669/cover-n.jpg","driveId":null},"abp-667":{"title":"ABP-667 Climax sex ACT.05 The limit of impatience that ","image":"https://fourhoi.com/abp-667/cover-n.jpg","driveId":null},"abp-668":{"title":"ABP-668 Endless Sex ACT.08 Series Most Radical Frenzy G","image":"https://fourhoi.com/abp-668/cover-n.jpg","driveId":null},"auks-084":{"title":"AUKS-084 Relatives Obscene Lesbian ~ Raw Spitting Lesbi","image":"https://fourhoi.com/auks-084/cover-n.jpg","driveId":null},"aukg-406":{"title":"AUKG-406 Nasty Madam and Batuichi Caregiver ~ Bewitchin","image":"https://fourhoi.com/aukg-406/cover-n.jpg","driveId":null},"aukg-407":{"title":"AUKG-407 Drunk Lesbian ~ Sake, Bikini, Woman, Woman ~ -","image":"https://fourhoi.com/aukg-407/cover-n.jpg","driveId":null},"aymd-001":{"title":"AYMD-001 Produced by Myself. AV actress Haruka Namiki (","image":"https://fourhoi.com/aymd-001/cover-n.jpg","driveId":null},"abba-365":{"title":"ABBA-365 While stimulating the glans with meat folds, t","image":"https://fourhoi.com/abba-365/cover-n.jpg","driveId":null},"ap-004":{"title":"AP-004 Aphrodite Hikari Nagisa - MissAV | Watch HD JAV ","image":"https://fourhoi.com/ap-004/cover-n.jpg","driveId":null},"ap-005":{"title":"AP-005 Aphrodite Akari Mitani - MissAV | Watch HD JAV O","image":"https://fourhoi.com/ap-005/cover-n.jpg","driveId":null},"avkh-177":{"title":"AVKH-177 Tojo Yuri - MissAV | Watch HD JAV Online | Fre","image":"https://fourhoi.com/avkh-177/cover-n.jpg","driveId":null},"abon-006":{"title":"ABON-006 Massive launch SEX BEST that repeats ejaculati","image":"https://fourhoi.com/abon-006/cover-n.jpg","driveId":null},"akdl-049":{"title":"AKDL-049 Slutty son brought to her mother Devilish ☆ Be","image":"https://fourhoi.com/akdl-049/cover-n.jpg","driveId":null},"akdl-048":{"title":"AKDL-048 Completely Subjective Real Chi ○ Poshikori pla","image":"https://fourhoi.com/akdl-048/cover-n.jpg","driveId":null},"apns-032":{"title":"APNS-032 &quot;I will continue to be seeded by my classmates","image":"https://fourhoi.com/apns-032/cover-n.jpg","driveId":null},"apnh-013":{"title":"APNH-013 New Chapter / After School Beautiful Girl H Ch","image":"https://fourhoi.com/apnh-013/cover-n.jpg","driveId":null},"apns-031":{"title":"APNS-031 During a long business trip for 30 days, my be","image":"https://fourhoi.com/apns-031/cover-n.jpg","driveId":null},"apkh-051":{"title":"APKH-051 Amane Yayoi, a beautiful girl in uniform of th","image":"https://fourhoi.com/apkh-051/cover-n.jpg","driveId":null},"avsw-050":{"title":"AVSW-050 AIKA world - Aika - MissAV | Watch HD JAV Onli","image":"https://fourhoi.com/avsw-050/cover-n.jpg","driveId":null},"avsa-048":{"title":"AVSA-048 ED ~ Erectile Dysfunction ~ Treatment Clinic D","image":"https://fourhoi.com/avsa-048/cover-n.jpg","driveId":null},"ambx-061":{"title":"AMBX-061 It ’s dangerous! I was picked up in the city a","image":"https://fourhoi.com/ambx-061/cover-n.jpg","driveId":null},"adn-144":{"title":"ADN-144 My husband is surely aware. Saeko Matsushita - ","image":"https://fourhoi.com/adn-144/cover-n.jpg","driveId":null},"adn-142":{"title":"ADN-142 Forgive me ... -Reunion gets wet with a nasty l","image":"https://fourhoi.com/adn-142/cover-n.jpg","driveId":null},"adn-145":{"title":"ADN-145 Fucked in front of her husband-Revisiting viole","image":"https://fourhoi.com/adn-145/cover-n.jpg","driveId":null},"adn-143":{"title":"ADN-143 Attic Sarasa Hara - Natsume Saiharu - MissAV | ","image":"https://fourhoi.com/adn-143/cover-n.jpg","driveId":null},"akid-046":{"title":"Aplay-046 Cuckold Limited ● Former classmates who came ","image":"https://fourhoi.com/akid-046/cover-n.jpg","driveId":null},"abp-664":{"title":"ABP-664 An Ultra High Class Secret Sexy Spa Salon 02 Se","image":"https://fourhoi.com/abp-664/cover-n.jpg","driveId":null},"akid-045":{"title":"Aplay-045 Female College Student Only After Drinking Pa","image":"https://fourhoi.com/akid-045/cover-n.jpg","driveId":null},"ama-005":{"title":"AMA-005 A masterpiece of SEX. Shocking test shots of di","image":"https://fourhoi.com/ama-005/cover-n.jpg","driveId":null},"abp-666":{"title":"ABP-666 Small Stop Small Devil Soap 3 Give You the Best","image":"https://fourhoi.com/abp-666/cover-n.jpg","driveId":null},"abp-665":{"title":"ABP-665 Kurokawa Sarina&#039;s finest brush wholesale 17 F c","image":"https://fourhoi.com/abp-665/cover-n.jpg","driveId":null},"any-002":{"title":"ANY-002 Tan Bishoujo Collection A collection of exquisi","image":"https://fourhoi.com/any-002/cover-n.jpg","driveId":null},"agemix-387":{"title":"AGEMIX-387 Deep throating from the side - a troubling p","image":"https://fourhoi.com/agemix-387/cover-n.jpg","driveId":null},"agemix-388":{"title":"AGEMIX-388 Waist swing ejaculation on the hand ma ● The","image":"https://fourhoi.com/agemix-388/cover-n.jpg","driveId":null},"agemix-386":{"title":"AGEMIX-386 Advanced fellatio by ambitious sluts - new t","image":"https://fourhoi.com/agemix-386/cover-n.jpg","driveId":null},"agemix-389":{"title":"AGEMIX-389 Beautiful mature women have serious sex with","image":"https://fourhoi.com/agemix-389/cover-n.jpg","driveId":null},"av-178":{"title":"AV-178 Fortune telling Miwako Hashimoto - MissAV | Watc","image":"https://fourhoi.com/av-178/cover-n.jpg","driveId":null},"ap-489":{"title":"AP-489 JK Health Examination Intercrural Sex Creampie S","image":"https://fourhoi.com/ap-489/cover-n.jpg","driveId":null},"ap-487":{"title":"AP-487 School Women&#039;s Toilet Hamesion Slut ● - MissAV |","image":"https://fourhoi.com/ap-487/cover-n.jpg","driveId":null},"ap-491":{"title":"AP-491 Inserted with OL pantyhose Massive ejaculation ●","image":"https://fourhoi.com/ap-491/cover-n.jpg","driveId":null},"ap-490":{"title":"AP-490 Hard Piston Deep Throating Bookstore Creampie Sl","image":"https://fourhoi.com/ap-490/cover-n.jpg","driveId":null},"atom-303":{"title":"ATOM-303 Only for school girls! Aim for a prize of 1 mi","image":"https://fourhoi.com/atom-303/cover-n.jpg","driveId":null},"atom-304":{"title":"ATOM-304 Immediately Porori &amp; Immediate Mantilla in 2 s","image":"https://fourhoi.com/atom-304/cover-n.jpg","driveId":null},"atom-305":{"title":"ATOM-305 Skirt &amp; Porori barrage! Mischievous patience R","image":"https://fourhoi.com/atom-305/cover-n.jpg","driveId":null},"ap-488":{"title":"AP-488 A busty woman found at a hot spring inn at night","image":"https://fourhoi.com/ap-488/cover-n.jpg","driveId":null},"atom-306":{"title":"ATOM-306 Only for amateur beautiful wives! Why don&#039;t yo","image":"https://fourhoi.com/atom-306/cover-n.jpg","driveId":null},"apkh-050":{"title":"APKH-050 Indecent sex with uniforms, futons and sweat d","image":"https://fourhoi.com/apkh-050/cover-n.jpg","driveId":null},"apkh-049":{"title":"APKH-049 Ikase cowgirl of paradise grind! The ultimate ","image":"https://fourhoi.com/apkh-049/cover-n.jpg","driveId":null},"apkh-048":{"title":"APKH-048 First shot debut &quot;Today, the taste of semen ..","image":"https://fourhoi.com/apkh-048/cover-n.jpg","driveId":null},"abp-663":{"title":"ABP-663 Derived from natural ingredients Yoshikawa lotu","image":"https://fourhoi.com/abp-663/cover-n.jpg","driveId":null},"abp-662":{"title":"ABP-662 I Live With My Girlfriend And She Has Multiple ","image":"https://fourhoi.com/abp-662/cover-n.jpg","driveId":null},"aka-048":{"title":"AKA-048 Let me take your AV as it is. 1 Miraculous 8-he","image":"https://fourhoi.com/aka-048/cover-n.jpg","driveId":null},"abp-661":{"title":"ABP-661 Life&#039;s first trance state Intense climax sex 40","image":"https://fourhoi.com/abp-661/cover-n.jpg","driveId":null},"abp-660":{"title":"ABP-660 I will lend you an absolute beautiful girl. Nat","image":"https://fourhoi.com/abp-660/cover-n.jpg","driveId":null},"apns-030":{"title":"APNS-030 Beautiful girl who was masturbating &quot;Help ... ","image":"https://fourhoi.com/apns-030/cover-n.jpg","driveId":null},"auks-083":{"title":"AUKS-083 Constricted huge breasts lesbian! Obscene unde","image":"https://fourhoi.com/auks-083/cover-n.jpg","driveId":null},"apns-029":{"title":"APNS-029 A beautiful law office worker who was crashed ","image":"https://fourhoi.com/apns-029/cover-n.jpg","driveId":null},"aukg-405":{"title":"AUKG-405 Married Women&#039;s Scheming Lesbians - If Only My","image":"https://fourhoi.com/aukg-405/cover-n.jpg","driveId":null},"aqsh-012":{"title":"AQSH-012 My wife was taken down. My wife, who I thought","image":"https://fourhoi.com/aqsh-012/cover-n.jpg","driveId":null},"abba-363":{"title":"ABBA-363 Fifty or More Hundred Flowers Ryoran Middle-ag","image":"https://fourhoi.com/abba-363/cover-n.jpg","driveId":null},"ap-485":{"title":"AP-485 Glasses girl JK mass ejaculation in black tights","image":"https://fourhoi.com/ap-485/cover-n.jpg","driveId":null},"ap-483":{"title":"AP-483 Inserted with library pantyhose Massive ejaculat","image":"https://fourhoi.com/ap-483/cover-n.jpg","driveId":null},"ap-482":{"title":"AP-482 Slut who bullied a cute Ubu girl who can not say","image":"https://fourhoi.com/ap-482/cover-n.jpg","driveId":null},"ap-486":{"title":"AP-486 Glans clitoris rubbing ● ~ Rubbing the clitoris ","image":"https://fourhoi.com/ap-486/cover-n.jpg","driveId":null},"ap-484":{"title":"AP-484 Big Breasts Rubbing, Chasing After, Creampie Slu","image":"https://fourhoi.com/ap-484/cover-n.jpg","driveId":null},"agr-023":{"title":"AGR-023 The wife next door is Mai Nanase, a J-cup feroc","image":"https://fourhoi.com/agr-023/cover-n.jpg","driveId":null},"anb-138":{"title":"ANB-138 Rieko Hiraoka, a beautiful and odious aunt&#039;s ob","image":"https://fourhoi.com/anb-138/cover-n.jpg","driveId":null},"ako-298":{"title":"AKO-298 EMIRI - MissAV | Watch HD JAV Online | Free &amp; H","image":"https://fourhoi.com/ako-298/cover-n.jpg","driveId":null},"aed-148":{"title":"AED-148 play Creampie Vagina For Fifty Mom Yayoi Mizuta","image":"https://fourhoi.com/aed-148/cover-n.jpg","driveId":null},"abp-656":{"title":"ABP-656 Mion Sonoda Lucky Lewd 2 All the erotic things ","image":"https://fourhoi.com/abp-656/cover-n.jpg","driveId":null},"ama-004":{"title":"AMA-004 A masterpiece of SEX. Shocking test shots of di","image":"https://fourhoi.com/ama-004/cover-n.jpg","driveId":null},"abp-657":{"title":"ABP-657 A Private Hot Springs Bath With A Beautiful Gir","image":"https://fourhoi.com/abp-657/cover-n.jpg","driveId":null},"afs-027":{"title":"AFS-027 Married Woman Picking Up Girls Home Creampie x ","image":"https://fourhoi.com/afs-027/cover-n.jpg","driveId":null},"abp-659":{"title":"ABP-659 Obedient pet only for me who likes me too much ","image":"https://fourhoi.com/abp-659/cover-n.jpg","driveId":null},"abp-658":{"title":"ABP-658 The female manager is our sexual processing pet","image":"https://fourhoi.com/abp-658/cover-n.jpg","driveId":null}}