{"jrzd-775":null,"jrzd-774":null,"jckl-183":null,"juy-332":null,"juy-343":null,"juy-346":null,"juy-342":null,"juy-339":null,"juy-344":null,"juy-341":null,"juy-345":null,"jjbk-001":null,"jrzd-773":null,"jrzd-772":null,"jufd-839":null,"jufd-828":null,"jufd-829":null,"juy-333":null,"jufd-838":null,"jufd-833":null,"jufd-831":null,"jufd-832":null,"juy-336":null,"juy-334":null,"jufd-836":null,"jufd-840":null,"juy-338":null,"juy-335":null,"juy-337":null,"jufd-835":null,"jufd-837":null,"jufd-834":null,"jufd-830":null,"jrzd-771":null,"juy-327":null,"juy-316":null,"juy-331":null,"juy-317":null,"juy-315":null,"juy-323":null,"juy-330":null,"juy-325":null,"juy-320":null,"juy-324":null,"juy-321":null,"juy-319":null,"juy-326":null,"jjpp-105":null,"jjpp-104":null,"jrzd-769":null,"jf-184":null,"jf-190":null,"jf-198":null,"jksr-314":null,"jksr-311":null,"jksr-312":null,"jksr-313":null,"jf-160":null,"jf-163":null,"jf-171":null,"jf-177":null,"juy-318":null,"jrzd-767":null,"juy-329":null,"jura-010":null,"juy-328":null,"jrzd-766":null,"jyma-002":null,"jjbk-035":null,"jyma-001":null,"jrzd-992":null,"jrzd-991":null,"jks-163":null,"jrzd-765":null,"jrzd-764":null,"jknk-065":null,"juy-304":null,"juy-300":null,"juy-303":null,"juy-310":null,"juy-313":null,"juy-314":null,"juy-306":null,"juy-308":null,"juy-309":null,"juy-311":null,"juy-312":null,"juy-305":null,"juy-301":null,"juy-302":null,"jufd-819":null,"jufd-813":null,"jufd-816":null,"jufd-821":null,"jufd-818":null,"jufd-823":null,"jufd-820":null,"jufd-824":null,"jufd-825":null,"jufd-822":null,"jufd-815":null,"jufd-817":null,"jura-009":null,"jrzd-763":null,"jufd-826":null,"jufd-827":null,"jlz-024":null}